protocrash/__init__.py
protocrash/__version__.py
protocrash/cli/__init__.py
protocrash/cli/analyze_command.py
protocrash/cli/fuzz_command.py
protocrash/cli/main.py
protocrash/cli/report_command.py
protocrash/cli/ui/__init__.py
protocrash/cli/ui/crash_viewer.py
protocrash/cli/ui/dashboard.py
protocrash/cli/ui/html_generator.py
protocrash/cli/ui/keyboard_handler.py
protocrash/core/__init__.py
protocrash/core/protocol_detector.py
protocrash/core/protocol_parser.py
protocrash/core/protocol_registry.py
protocrash/core/types.py
protocrash/distributed/__init__.py
protocrash/distributed/coordinator.py
protocrash/distributed/corpus_sync.py
protocrash/distributed/stats_aggregator.py
protocrash/distributed/worker.py
protocrash/fuzzing_engine/__init__.py
protocrash/fuzzing_engine/coordinator.py
protocrash/fuzzing_engine/corpus.py
protocrash/fuzzing_engine/scheduler.py
protocrash/fuzzing_engine/stats.py
protocrash/monitors/__init__.py
protocrash/monitors/coverage.py
protocrash/monitors/coverage_analyzer.py
protocrash/monitors/coverage_comparator.py
protocrash/monitors/coverage_map.py
protocrash/monitors/crash_bucketing.py
protocrash/monitors/crash_classifier.py
protocrash/monitors/crash_database.py
protocrash/monitors/crash_detector.py
protocrash/monitors/crash_minimizer.py
protocrash/monitors/crash_reporter.py
protocrash/monitors/execution_monitor.py
protocrash/monitors/memory_leak_detector.py
protocrash/monitors/stack_trace_parser.py
protocrash/mutators/__init__.py
protocrash/mutators/binary_mutator.py
protocrash/mutators/deterministic.py
protocrash/mutators/dictionary.py
protocrash/mutators/dns_mutator.py
protocrash/mutators/havoc.py
protocrash/mutators/http_mutator.py
protocrash/mutators/mutation_engine.py
protocrash/mutators/smtp_mutator.py
protocrash/mutators/splice.py
protocrash/parsers/__init__.py
protocrash/parsers/binary_parser.py
protocrash/parsers/dns_parser.py
protocrash/parsers/http_parser.py
protocrash/parsers/smtp_parser.py
protocrash-1.0.0.dist-info/licenses/LICENSE
protocrash-1.0.0.dist-info/METADATA
protocrash-1.0.0.dist-info/WHEEL
protocrash-1.0.0.dist-info/entry_points.txt
protocrash-1.0.0.dist-info/top_level.txt
protocrash-1.0.0.dist-info/RECORD
