Metadata-Version: 2.4
Name: protocrash
Version: 1.0.0
Summary: Coverage-guided protocol fuzzer for security testing
Home-page: https://github.com/noobforanonymous/ProtoCrash
Author: Regaan
Author-email: Regaan <regaan48@gmail.com>
License: MIT
Project-URL: Homepage, https://github.com/noobforanonymous/ProtoCrash
Project-URL: Documentation, https://github.com/noobforanonymous/ProtoCrash/tree/main/docs
Project-URL: Repository, https://github.com/noobforanonymous/ProtoCrash.git
Project-URL: Issues, https://github.com/noobforanonymous/ProtoCrash/issues
Keywords: fuzzing,security,protocol,testing,vulnerability
Classifier: Development Status :: 4 - Beta
Classifier: Intended Audience :: Developers
Classifier: License :: OSI Approved :: MIT License
Classifier: Programming Language :: Python :: 3.11
Classifier: Programming Language :: Python :: 3.12
Classifier: Topic :: Security
Requires-Python: >=3.11
License-File: LICENSE
Requires-Dist: click>=8.1.0
Requires-Dist: rich>=13.0.0
Requires-Dist: pwntools>=4.10.0
Requires-Dist: scapy>=2.5.0
Requires-Dist: psutil>=5.9.0
Requires-Dist: pyyaml>=6.0
Requires-Dist: numpy>=1.24.0
Provides-Extra: dev
Requires-Dist: pytest>=7.4.0; extra == "dev"
Requires-Dist: pytest-cov>=4.1.0; extra == "dev"
Requires-Dist: pytest-mock>=3.11.0; extra == "dev"
Requires-Dist: pytest-timeout>=2.1.0; extra == "dev"
Requires-Dist: ruff>=0.1.0; extra == "dev"
Requires-Dist: black>=23.0.0; extra == "dev"
Requires-Dist: mypy>=1.5.0; extra == "dev"
Requires-Dist: pre-commit>=3.4.0; extra == "dev"
Requires-Dist: types-PyYAML>=6.0.0; extra == "dev"
Requires-Dist: types-psutil>=5.9.0; extra == "dev"
Dynamic: author
Dynamic: home-page
Dynamic: license-file
Dynamic: requires-python
